aws_cost_optimization_10/__init__.py
aws_cost_optimization_10/_cloudwatch_costing.py
aws_cost_optimization_10/_ec2_costing.py
aws_cost_optimization_10/_elb_costing.py
aws_cost_optimization_10/_kms_costing.py
aws_cost_optimization_10/_rds_costing.py
aws_cost_optimization_10/_ri_recommendations.py
aws_cost_optimization_10/_savings_plan.py
aws_cost_optimization_10/utils.py
aws_cost_optimization_10-0.2.9.dist-info/LICENCE
aws_cost_optimization_10-0.2.9.dist-info/METADATA
aws_cost_optimization_10-0.2.9.dist-info/WHEEL
aws_cost_optimization_10-0.2.9.dist-info/top_level.txt
aws_cost_optimization_10-0.2.9.dist-info/RECORD
